scanning_drift_corr/SPmakeImage.py
scanning_drift_corr/SPmerge01linear.py
scanning_drift_corr/SPmerge02.py
scanning_drift_corr/SPmerge02_final.py
scanning_drift_corr/SPmerge02_initial.py
scanning_drift_corr/SPmerge02_phase_correlation.py
scanning_drift_corr/SPmerge03.py
scanning_drift_corr/__init__.py
scanning_drift_corr/api.py
scanning_drift_corr/sMerge.py
scanning_drift_corr/tools.py
scanning_drift_corr/examples/example.ipynb
scanning_drift_corr/examples/example.py
scanning_drift_corr/tests/nonlinear_drift_correction_synthetic_dataset_for_testing.mat
scanning_drift_corr-1.0.1.dist-info/LICENCE
scanning_drift_corr-1.0.1.dist-info/METADATA
scanning_drift_corr-1.0.1.dist-info/WHEEL
scanning_drift_corr-1.0.1.dist-info/top_level.txt
scanning_drift_corr-1.0.1.dist-info/RECORD
