Metadata-Version: 2.1
Name: scanning-drift-corr
Version: 1.0.1
Summary: Correct scan drift distortion
Home-page: https://github.com/ptim0626/scanning-drift-corr
Author: Timothy Poon
Author-email: timothy0626@gmail.com
License: UNKNOWN
Project-URL: Bug Tracker, https://github.com/ptim0626/scanning-drift-corr/issues
Platform: UNKNOWN
Classifier: Programming Language :: Python :: 3
Classifier: License :: OSI Approved :: MIT License
Classifier: Operating System :: OS Independent
Requires-Python: >=3.8
License-File: LICENCE
Requires-Dist: numpy
Requires-Dist: matplotlib
Requires-Dist: scipy
Requires-Dist: tqdm
Requires-Dist: h5py
Provides-Extra: tests
Requires-Dist: pytest ; extra == 'tests'
